graphql_alchemy/__init__.py
graphql_alchemy/const.py
graphql_alchemy/utils.py
graphql_alchemy/converter/__init__.py
graphql_alchemy/converter/base.py
graphql_alchemy/converter/dataclass_.py
graphql_alchemy/converter/dict_.py
graphql_alchemy/converter/pydantic_.py
graphql_alchemy/types/__init__.py
graphql_alchemy/types/base.py
graphql_alchemy/types/enums.py
graphql_alchemy/types/query.py
graphql_alchemy-0.0.4.dist-info/licenses/LICENSE
graphql_alchemy-0.0.4.dist-info/METADATA
graphql_alchemy-0.0.4.dist-info/WHEEL
graphql_alchemy-0.0.4.dist-info/top_level.txt
graphql_alchemy-0.0.4.dist-info/RECORD
