Metadata-Version: 2.4
Name: graphql-alchemy
Version: 0.0.4
Summary: Graph ql client library
Author: Artur Youngblood
Author-email: Artur Youngblood <arturungb@gmail.com>
License-Expression: MIT
Project-URL: Homepage, https://github.com/pypa/graphql-alchemy
Classifier: Development Status :: 4 - Beta
Classifier: Programming Language :: Python :: 3.11
Classifier: Programming Language :: Python :: 3.12
Classifier: Topic :: Software Development :: Libraries :: Python Modules
Requires-Python: >=3.12
License-File: LICENSE
Requires-Dist: pydantic>=2.12.3
Requires-Dist: pytest>=8.4.2
Requires-Dist: pytest-coverage>=0.0
Requires-Dist: python-graphql-client>=0.4.3
Dynamic: author
Dynamic: license-file
